{
    "volume": "14",
    "issue": "06",
    "year": "1999",
    "month": "11-12",
    "mname": "ದ್ವೈಮಾಸಿಕ",
    "id": "003/1999/11-12",
    "toc": [
        {
            "title": "ಸಂಪಾದಕೀಯ",
            "page": "000d"
        },
        {
            "title": "ಗುರುವಾಣಿ",
            "page": "000f"
        },
        {
            "title": "ಮೈಸೂರು ಮತ್ತು ಚಾಮರಾಜನಗರ ಜಿಲ್ಲೆಗಳ ವಚನಕಾರರ ವಚನ ಮತ್ತು ಅರ ವಚನ ಸಾಹಿತ್ಯದ ಸಮೀಕ್ಷೆ",
            "page": "0003-0018",
            "relativePageNumber": 1,
            "relativePageRange": "1-1",
            "fullText": [],
            "author": [
                {
                    "name": "ಎ. ಎಸ್. ಜಯರಾಂ"
                }
            ]
        },
        {
            "title": "ಸಂಸ್ಕೃತಸುಬಾಷಿತಗಳಲ್ಲಿ ಹಾಸ್ಯ",
            "page": "0019-0026",
            "relativePageNumber": 1,
            "relativePageRange": "1-1",
            "fullText": [],
            "author": [
                {
                    "name": "ಎಚ್. ವಿ. ನಾಗರಾಜರಾವ್"
                }
            ]
        },
        {
            "title": "ಮಹಿಳೆ-ಸಮಾಜ-ನಾವು",
            "page": "0027-0032",
            "relativePageNumber": 1,
            "relativePageRange": "1-1",
            "fullText": [],
            "author": [
                {
                    "name": "ಡಾ. ಕಮಲಾ ಹಂಪನಾ"
                }
            ]
        },
        {
            "title": "ಪದಾಂತ್ಯ ಬಿಂದುವೋ ಪದಮಧ್ಯವಿಂದುವೋ?:ಒಂದು ನಿರ್ಣಯ",
            "page": "0033-0038",
            "relativePageNumber": 1,
            "relativePageRange": "1-1",
            "fullText": [],
            "author": [
                {
                    "name": "ಪ್ರೊ. ಸಿ. ಮಹಾದೇವಪ್ಪ"
                }
            ]
        },
        {
            "title": "ರಾಷ್ಟ್ರೀಯಹಬ್ಬ ದೀಪಾವಳಿ",
            "page": "0039-0043",
            "relativePageNumber": 1,
            "relativePageRange": "1-1",
            "fullText": [],
            "author": [
                {
                    "name": "ಅನುರಾಧ ಪಟೇಲ್"
                }
            ]
        },
        {
            "title": "ವಚನಗಳ ಉಗಮ ಮತ್ತು ಉದ್ದೇಶ",
            "page": "0044-0048",
            "relativePageNumber": 1,
            "relativePageRange": "1-1",
            "fullText": [],
            "author": [
                {
                    "name": "ಡಾ. ಎಸ್. ವಿ. ಪ್ರಭಾವತಿ"
                }
            ]
        },
        {
            "title": "ಶರಣ ಸ್ಥಲ",
            "page": "0049-0052",
            "relativePageNumber": 1,
            "relativePageRange": "1-1",
            "fullText": [],
            "author": [
                {
                    "name": "ಡಾ. ಎಸ್. ಆರ್. ಗುಂಜಾಳ್"
                }
            ]
        }
    ]
}