{
    "volume": "08",
    "issue": "04",
    "year": "1978",
    "month": "04",
    "mname": "ಚೈತ್ರ ಸಂಚಿಕೆ (ಏಪ್ರಿಲ್",
    "id": "003/1978/04",
    "toc": [
        {
            "title": "ಪ್ರಸಾದ ವಿನಿಯೋಗಕ್ಕೆ ಮುನ್ನ-ಸಂಪಾದಕೀಯ",
            "page": "iv"
        },
        {
            "title": "ವೇದಾದೇಶ",
            "page": "v",
            "author": [
                {
                    "name": "ವಿದ್ವಾನ್ ಎಂ. ಜಿ. ನಂಜುಂಡಾರಾಧ್ಯ"
                }
            ]
        },
        {
            "title": "ಅಲ್ಲಮ ಮತ್ತು ಮುಕ್ತಾಯಿ (ಒಂದು ಅಪೂರ್ವ ಸಂಗಮ)",
            "page": "0001-0008",
            "relativePageNumber": 1,
            "relativePageRange": "1-1",
            "fullText": [],
            "author": [
                {
                    "name": "ಡಿ. ಎಂ. ಮಹದೇವಮೂರ್ತಿ"
                }
            ]
        },
        {
            "title": "ಶಬ್ದಾಂಜಲಿ",
            "page": "0009-0009",
            "relativePageNumber": 1,
            "relativePageRange": "1-1",
            "fullText": [],
            "author": [
                {
                    "name": "ಎಸ್. ಎಸ್. ಭೂಸರೆಡ್ಡಿ"
                }
            ]
        },
        {
            "title": "ಮಹಾಪ್ರಸಾದಿ",
            "page": "0010-0015",
            "relativePageNumber": 1,
            "relativePageRange": "1-1",
            "fullText": [],
            "author": [
                {
                    "name": "ಎಂ. ಎ. ನೀಲಾಂಬಿಕಾ"
                }
            ]
        },
        {
            "title": "“ಪ್ರಕೃತಿ-ಶೈತ್ಯಾಲಯಗಳ ಬಗ್ಗೆ ಕೇಳಿದ್ದೀರಾ”",
            "page": "0016-0022",
            "relativePageNumber": 1,
            "relativePageRange": "1-1",
            "fullText": [],
            "author": [
                {
                    "name": "ಸಿ. ಬಿ. ಪ್ರಭುದೇವಸ್ವಾಮಿ"
                }
            ]
        },
        {
            "title": "ವಚನಗಳು",
            "page": "0023-0024",
            "relativePageNumber": 1,
            "relativePageRange": "1-1",
            "fullText": [],
            "author": [
                {
                    "name": "ಜೀಮಾರಹಳ್ಳಿ ವೀರಣ್ಣ"
                }
            ]
        },
        {
            "title": "ಶಬರಲೀಲೆಯಲ್ಲಿ ಕಲಿಪಾರ್ಥಾ",
            "page": "0025-0046",
            "relativePageNumber": 1,
            "relativePageRange": "1-1",
            "fullText": [],
            "author": [
                {
                    "name": "ಹೆಚ್. ಗಂಗಾಧರ್ರ"
                }
            ]
        },
        {
            "title": "ಮೈಸೂರು ಜಿಲ್ಲಾ ವೀರಶೈವ ಮಠಾದೀಶ್ವರರುಗಳ ಸಮ್ಮೇಳನ",
            "page": "0047-0048",
            "relativePageNumber": 1,
            "relativePageRange": "1-1",
            "fullText": []
        },
        {
            "title": "ವಾರ್ತಾ ವಿಹಾರ",
            "page": "0049-0053",
            "relativePageNumber": 1,
            "relativePageRange": "1-1",
            "fullText": []
        },
        {
            "title": "ಸಾದರ ಸ್ವೀಕಾರ",
            "page": "0054-0056",
            "relativePageNumber": 1,
            "relativePageRange": "1-1",
            "fullText": []
        },
        {
            "title": "ಈ ಸಂಚಿಕೆಯ ಲೇಖಕರು",
            "page": "0057-0057",
            "relativePageNumber": 1,
            "relativePageRange": "1-1",
            "fullText": []
        }
    ]
}